Damen_profiling_tools/__init__.py
Damen_profiling_tools/dataprofile.py
damen_profiling_tools-0.0.6.dist-info/METADATA
damen_profiling_tools-0.0.6.dist-info/WHEEL
damen_profiling_tools-0.0.6.dist-info/top_level.txt
damen_profiling_tools-0.0.6.dist-info/RECORD
