Metadata-Version: 2.4
Name: Damen_profiling_tools
Version: 0.0.6
Summary: Damen-library
Author-email: giandaeky <giandaekyoga10@gmail.com>
License: MIT
Project-URL: Homepage, https://pypi.org/project/Damen_profiling_tools/
Requires-Python: >=3.8
